{
  "type": "FeatureCollection",
  "features": [
    {
      "type": "Feature",
      "geometry": {
        "type": "Point",
        "coordinates": [31.810859999999998, -24.72041]
      },
      "properties": { "name": "value0" }
    },
    {
      "type": "Feature",
      "geometry": {
        "type": "Point",
        "coordinates": [31.812109999999997, -24.72042]
      },
      "properties": { "name": "value1" }
    },
    {
      "type": "Feature",
      "geometry": {
        "type": "Point",
        "coordinates": [31.815179999999998, -24.72014]
      },
      "properties": { "name": "value2" }
    },
    {
      "type": "Feature",
      "geometry": {
        "type": "Point",
        "coordinates": [31.8156199999999, -24.71988]
      },
      "properties": { "name": "value3" }
    },
    {
      "type": "Feature",
      "geometry": {
        "type": "Point",
        "coordinates": [31.30975, -25.0018999999999]
      },
      "properties": { "name": "value4" }
    },
    {
      "type": "Feature",
      "geometry": {
        "type": "Point",
        "coordinates": [31.8157099999999, -24.71985]
      },
      "properties": { "name": "value5" }
    },
    {
      "type": "Feature",
      "geometry": {
        "type": "Point",
        "coordinates": [31.30824, -25.002589999999998]
      },
      "properties": { "name": "value6" }
    },
    {
      "type": "Feature",
      "geometry": {
        "type": "Point",
        "coordinates": [31.8124499999999, -24.7208299999999]
      },
      "properties": { "name": "value7" }
    },
    {
      "type": "Feature",
      "geometry": { "type": "Point", "coordinates": [31.30527, -25.00366] },
      "properties": { "name": "value8" }
    },
    {
      "type": "Feature",
      "geometry": {
        "type": "Point",
        "coordinates": [31.810209999999998, -24.72372]
      },
      "properties": { "name": "value9" }
    },
    {
      "type": "Feature",
      "geometry": {
        "type": "Point",
        "coordinates": [31.301709999999996, -25.005229999999997]
      },
      "properties": { "name": "value10" }
    },
    {
      "type": "Feature",
      "geometry": {
        "type": "Point",
        "coordinates": [31.30228, -25.009079999999997]
      },
      "properties": { "name": "value11" }
    },
    {
      "type": "Feature",
      "geometry": {
        "type": "Point",
        "coordinates": [31.8087, -24.7250599999999]
      },
      "properties": { "name": "value12" }
    },
    {
      "type": "Feature",
      "geometry": {
        "type": "Point",
        "coordinates": [31.8078399999999, -24.7263799999999]
      },
      "properties": { "name": "value13" }
    },
    {
      "type": "Feature",
      "geometry": {
        "type": "Point",
        "coordinates": [31.30214, -25.0082899999999]
      },
      "properties": { "name": "value14" }
    },
    {
      "type": "Feature",
      "geometry": {
        "type": "Point",
        "coordinates": [31.806390000000004, -24.7279599999999]
      },
      "properties": { "name": "value15" }
    },
    {
      "type": "Feature",
      "geometry": {
        "type": "Point",
        "coordinates": [31.3022199999999, -25.01473]
      },
      "properties": { "name": "value16" }
    },
    {
      "type": "Feature",
      "geometry": {
        "type": "Point",
        "coordinates": [31.80289, -24.734679999999997]
      },
      "properties": { "name": "value17" }
    },
    {
      "type": "Feature",
      "geometry": {
        "type": "Point",
        "coordinates": [31.30232, -25.0158999999999]
      },
      "properties": { "name": "value18" }
    },
    {
      "type": "Feature",
      "geometry": {
        "type": "Point",
        "coordinates": [31.7962799999999, -24.7422]
      },
      "properties": { "name": "value19" }
    },
    {
      "type": "Feature",
      "geometry": {
        "type": "Point",
        "coordinates": [31.303459999999998, -25.01577]
      },
      "properties": { "name": "value20" }
    },
    {
      "type": "Feature",
      "geometry": {
        "type": "Point",
        "coordinates": [31.796090000000003, -24.74247]
      },
      "properties": { "name": "value21" }
    },
    {
      "type": "Feature",
      "geometry": {
        "type": "Point",
        "coordinates": [31.7955299999999, -24.742829999999998]
      },
      "properties": { "name": "value22" }
    },
    {
      "type": "Feature",
      "geometry": {
        "type": "Point",
        "coordinates": [31.7943, -24.743129999999997]
      },
      "properties": { "name": "value23" }
    },
    {
      "type": "Feature",
      "geometry": {
        "type": "Point",
        "coordinates": [31.3042599999999, -25.01921]
      },
      "properties": { "name": "value24" }
    },
    {
      "type": "Feature",
      "geometry": { "type": "Point", "coordinates": [31.79295, -24.74292] },
      "properties": { "name": "value25" }
    },
    {
      "type": "Feature",
      "geometry": {
        "type": "Point",
        "coordinates": [31.305, -25.0196599999999]
      },
      "properties": { "name": "value26" }
    },
    {
      "type": "Feature",
      "geometry": { "type": "Point", "coordinates": [31.79175, -24.74288] },
      "properties": { "name": "value27" }
    },
    {
      "type": "Feature",
      "geometry": {
        "type": "Point",
        "coordinates": [31.79128, -24.7418699999999]
      },
      "properties": { "name": "value28" }
    },
    {
      "type": "Feature",
      "geometry": {
        "type": "Point",
        "coordinates": [31.79233, -24.7414899999999]
      },
      "properties": { "name": "value29" }
    },
    {
      "type": "Feature",
      "geometry": {
        "type": "Point",
        "coordinates": [31.3089499999999, -25.0196499999999]
      },
      "properties": { "name": "value30" }
    },
    {
      "type": "Feature",
      "geometry": {
        "type": "Point",
        "coordinates": [31.7936699999999, -24.74155]
      },
      "properties": { "name": "value31" }
    },
    {
      "type": "Feature",
      "geometry": {
        "type": "Point",
        "coordinates": [31.3090599999999, -25.0198299999999]
      },
      "properties": { "name": "value32" }
    },
    {
      "type": "Feature",
      "geometry": {
        "type": "Point",
        "coordinates": [31.79465, -24.741889999999998]
      },
      "properties": { "name": "value33" }
    },
    {
      "type": "Feature",
      "geometry": {
        "type": "Point",
        "coordinates": [31.7938599999999, -24.7407399999999]
      },
      "properties": { "name": "value34" }
    },
    {
      "type": "Feature",
      "geometry": { "type": "Point", "coordinates": [31.79397, -24.74151] },
      "properties": { "name": "value35" }
    },
    {
      "type": "Feature",
      "geometry": {
        "type": "Point",
        "coordinates": [31.79402, -24.741629999999997]
      },
      "properties": { "name": "value36" }
    },
    {
      "type": "Feature",
      "geometry": { "type": "Point", "coordinates": [31.30767, -25.02371] },
      "properties": { "name": "value37" }
    },
    {
      "type": "Feature",
      "geometry": {
        "type": "Point",
        "coordinates": [31.306929999999998, -25.02465]
      },
      "properties": { "name": "value38" }
    },
    {
      "type": "Feature",
      "geometry": { "type": "Point", "coordinates": [31.79397, -24.74175] },
      "properties": { "name": "value39" }
    },
    {
      "type": "Feature",
      "geometry": {
        "type": "Point",
        "coordinates": [31.3066, -25.0249899999999]
      },
      "properties": { "name": "value40" }
    },
    {
      "type": "Feature",
      "geometry": { "type": "Point", "coordinates": [31.79393, -24.74155] },
      "properties": { "name": "value41" }
    },
    {
      "type": "Feature",
      "geometry": { "type": "Point", "coordinates": [31.79372, -24.74175] },
      "properties": { "name": "value42" }
    },
    {
      "type": "Feature",
      "geometry": {
        "type": "Point",
        "coordinates": [31.3041799999999, -25.02709]
      },
      "properties": { "name": "value43" }
    },
    {
      "type": "Feature",
      "geometry": {
        "type": "Point",
        "coordinates": [31.7943399999999, -24.7415999999999]
      },
      "properties": { "name": "value44" }
    },
    {
      "type": "Feature",
      "geometry": {
        "type": "Point",
        "coordinates": [31.30452, -25.0261199999999]
      },
      "properties": { "name": "value45" }
    },
    {
      "type": "Feature",
      "geometry": {
        "type": "Point",
        "coordinates": [31.795009999999998, -24.74156]
      },
      "properties": { "name": "value46" }
    },
    {
      "type": "Feature",
      "geometry": {
        "type": "Point",
        "coordinates": [31.3058799999999, -25.0243499999999]
      },
      "properties": { "name": "value47" }
    },
    {
      "type": "Feature",
      "geometry": {
        "type": "Point",
        "coordinates": [31.305640000000004, -25.023239999999998]
      },
      "properties": { "name": "value48" }
    },
    {
      "type": "Feature",
      "geometry": { "type": "Point", "coordinates": [31.30527, -25.02308] },
      "properties": { "name": "value49" }
    },
    {
      "type": "Feature",
      "geometry": { "type": "Point", "coordinates": [31.30387, -25.02352] },
      "properties": { "name": "value50" }
    },
    {
      "type": "Feature",
      "geometry": {
        "type": "Point",
        "coordinates": [31.300559999999997, -25.0252799999999]
      },
      "properties": { "name": "value51" }
    },
    {
      "type": "Feature",
      "geometry": {
        "type": "Point",
        "coordinates": [31.30047, -25.0260099999999]
      },
      "properties": { "name": "value52" }
    },
    {
      "type": "Feature",
      "geometry": { "type": "Point", "coordinates": [31.80185, -24.7389] },
      "properties": { "name": "value53" }
    },
    {
      "type": "Feature",
      "geometry": { "type": "Point", "coordinates": [31.30074, -25.02619] },
      "properties": { "name": "value54" }
    },
    {
      "type": "Feature",
      "geometry": { "type": "Point", "coordinates": [31.80227, -24.7387] },
      "properties": { "name": "value55" }
    },
    {
      "type": "Feature",
      "geometry": {
        "type": "Point",
        "coordinates": [31.30048, -25.0265799999999]
      },
      "properties": { "name": "value56" }
    },
    {
      "type": "Feature",
      "geometry": {
        "type": "Point",
        "coordinates": [31.30077, -25.0264099999999]
      },
      "properties": { "name": "value57" }
    },
    {
      "type": "Feature",
      "geometry": {
        "type": "Point",
        "coordinates": [31.30082, -25.0263199999999]
      },
      "properties": { "name": "value58" }
    },
    {
      "type": "Feature",
      "geometry": { "type": "Point", "coordinates": [31.803, -24.73881] },
      "properties": { "name": "value59" }
    },
    {
      "type": "Feature",
      "geometry": {
        "type": "Point",
        "coordinates": [31.3010699999999, -25.0262899999999]
      },
      "properties": { "name": "value60" }
    },
    {
      "type": "Feature",
      "geometry": {
        "type": "Point",
        "coordinates": [31.8032499999999, -24.7387699999999]
      },
      "properties": { "name": "value61" }
    },
    {
      "type": "Feature",
      "geometry": {
        "type": "Point",
        "coordinates": [31.30167, -25.027279999999998]
      },
      "properties": { "name": "value62" }
    },
    {
      "type": "Feature",
      "geometry": {
        "type": "Point",
        "coordinates": [31.3016499999999, -25.02756]
      },
      "properties": { "name": "value63" }
    },
    {
      "type": "Feature",
      "geometry": { "type": "Point", "coordinates": [31.30204, -25.02807] },
      "properties": { "name": "value64" }
    },
    {
      "type": "Feature",
      "geometry": {
        "type": "Point",
        "coordinates": [31.8064199999999, -24.73741]
      },
      "properties": { "name": "value65" }
    },
    {
      "type": "Feature",
      "geometry": {
        "type": "Point",
        "coordinates": [31.3031599999999, -25.0293199999999]
      },
      "properties": { "name": "value66" }
    },
    {
      "type": "Feature",
      "geometry": {
        "type": "Point",
        "coordinates": [31.303379999999997, -25.02964]
      },
      "properties": { "name": "value67" }
    },
    {
      "type": "Feature",
      "geometry": { "type": "Point", "coordinates": [31.30384, -25.02982] },
      "properties": { "name": "value68" }
    },
    {
      "type": "Feature",
      "geometry": { "type": "Point", "coordinates": [31.30368, -25.03003] },
      "properties": { "name": "value69" }
    },
    {
      "type": "Feature",
      "geometry": {
        "type": "Point",
        "coordinates": [31.304159999999996, -25.03002]
      },
      "properties": { "name": "value70" }
    },
    {
      "type": "Feature",
      "geometry": {
        "type": "Point",
        "coordinates": [31.3052899999999, -25.0299699999999]
      },
      "properties": { "name": "value71" }
    },
    {
      "type": "Feature",
      "geometry": { "type": "Point", "coordinates": [31.81108, -24.73607] },
      "properties": { "name": "value72" }
    },
    {
      "type": "Feature",
      "geometry": {
        "type": "Point",
        "coordinates": [31.305999999999997, -25.0296699999999]
      },
      "properties": { "name": "value73" }
    },
    {
      "type": "Feature",
      "geometry": {
        "type": "Point",
        "coordinates": [31.81117, -24.735879999999998]
      },
      "properties": { "name": "value74" }
    },
    {
      "type": "Feature",
      "geometry": {
        "type": "Point",
        "coordinates": [31.3068099999999, -25.029989999999998]
      },
      "properties": { "name": "value75" }
    },
    {
      "type": "Feature",
      "geometry": {
        "type": "Point",
        "coordinates": [31.8114999999999, -24.7358599999999]
      },
      "properties": { "name": "value76" }
    },
    {
      "type": "Feature",
      "geometry": { "type": "Point", "coordinates": [31.30834, -25.02944] },
      "properties": { "name": "value77" }
    },
    {
      "type": "Feature",
      "geometry": {
        "type": "Point",
        "coordinates": [31.81185, -24.735889999999998]
      },
      "properties": { "name": "value78" }
    },
    {
      "type": "Feature",
      "geometry": {
        "type": "Point",
        "coordinates": [31.3091599999999, -25.0293899999999]
      },
      "properties": { "name": "value79" }
    },
    {
      "type": "Feature",
      "geometry": { "type": "Point", "coordinates": [31.81219, -24.73565] },
      "properties": { "name": "value80" }
    },
    {
      "type": "Feature",
      "geometry": {
        "type": "Point",
        "coordinates": [31.310409999999997, -25.029429999999998]
      },
      "properties": { "name": "value81" }
    },
    {
      "type": "Feature",
      "geometry": {
        "type": "Point",
        "coordinates": [31.8131799999999, -24.73507]
      },
      "properties": { "name": "value82" }
    },
    {
      "type": "Feature",
      "geometry": {
        "type": "Point",
        "coordinates": [31.311259999999997, -25.0285699999999]
      },
      "properties": { "name": "value83" }
    },
    {
      "type": "Feature",
      "geometry": { "type": "Point", "coordinates": [31.81369, -24.73462] },
      "properties": { "name": "value84" }
    },
    {
      "type": "Feature",
      "geometry": {
        "type": "Point",
        "coordinates": [31.3121399999999, -25.0267699999999]
      },
      "properties": { "name": "value85" }
    },
    {
      "type": "Feature",
      "geometry": {
        "type": "Point",
        "coordinates": [31.8141, -24.734379999999998]
      },
      "properties": { "name": "value86" }
    },
    {
      "type": "Feature",
      "geometry": { "type": "Point", "coordinates": [31.31237, -25.02634] },
      "properties": { "name": "value87" }
    },
    {
      "type": "Feature",
      "geometry": {
        "type": "Point",
        "coordinates": [31.8154399999999, -24.7333]
      },
      "properties": { "name": "value88" }
    },
    {
      "type": "Feature",
      "geometry": { "type": "Point", "coordinates": [31.31185, -25.02522] },
      "properties": { "name": "value89" }
    },
    {
      "type": "Feature",
      "geometry": { "type": "Point", "coordinates": [31.81502, -24.73255] },
      "properties": { "name": "value90" }
    },
    {
      "type": "Feature",
      "geometry": {
        "type": "Point",
        "coordinates": [31.3109199999999, -25.02562]
      },
      "properties": { "name": "value91" }
    },
    {
      "type": "Feature",
      "geometry": {
        "type": "Point",
        "coordinates": [31.8138499999999, -24.73081]
      },
      "properties": { "name": "value92" }
    },
    {
      "type": "Feature",
      "geometry": {
        "type": "Point",
        "coordinates": [31.310809999999996, -25.0248099999999]
      },
      "properties": { "name": "value93" }
    },
    {
      "type": "Feature",
      "geometry": {
        "type": "Point",
        "coordinates": [31.81369, -24.7279699999999]
      },
      "properties": { "name": "value94" }
    },
    {
      "type": "Feature",
      "geometry": { "type": "Point", "coordinates": [31.3106, -25.02286] },
      "properties": { "name": "value95" }
    },
    {
      "type": "Feature",
      "geometry": {
        "type": "Point",
        "coordinates": [31.3077499999999, -25.022289999999998]
      },
      "properties": { "name": "value96" }
    },
    {
      "type": "Feature",
      "geometry": {
        "type": "Point",
        "coordinates": [31.3073599999999, -25.02347]
      },
      "properties": { "name": "value97" }
    },
    {
      "type": "Feature",
      "geometry": { "type": "Point", "coordinates": [31.81519, -24.72265] },
      "properties": { "name": "value98" }
    },
    {
      "type": "Feature",
      "geometry": {
        "type": "Point",
        "coordinates": [31.307059999999996, -25.0236899999999]
      },
      "properties": { "name": "value99" }
    },
    {
      "type": "Feature",
      "geometry": {
        "type": "Point",
        "coordinates": [31.306590000000003, -25.02295]
      },
      "properties": { "name": "value100" }
    },
    {
      "type": "Feature",
      "geometry": {
        "type": "Point",
        "coordinates": [31.8158199999999, -24.7204599999999]
      },
      "properties": { "name": "value101" }
    },
    {
      "type": "Feature",
      "geometry": {
        "type": "Point",
        "coordinates": [31.8160799999999, -24.7202799999999]
      },
      "properties": { "name": "value102" }
    },
    {
      "type": "Feature",
      "geometry": {
        "type": "Point",
        "coordinates": [31.30677, -25.022879999999997]
      },
      "properties": { "name": "value103" }
    },
    {
      "type": "Feature",
      "geometry": {
        "type": "Point",
        "coordinates": [31.3067099999999, -25.02298]
      },
      "properties": { "name": "value104" }
    },
    {
      "type": "Feature",
      "geometry": { "type": "Point", "coordinates": [31.80702, -24.72201] },
      "properties": { "name": "value105" }
    },
    {
      "type": "Feature",
      "geometry": { "type": "Point", "coordinates": [31.80547, -24.72256] },
      "properties": { "name": "value106" }
    },
    {
      "type": "Feature",
      "geometry": { "type": "Point", "coordinates": [31.30704, -25.02305] },
      "properties": { "name": "value107" }
    },
    {
      "type": "Feature",
      "geometry": {
        "type": "Point",
        "coordinates": [31.8045399999999, -24.7225499999999]
      },
      "properties": { "name": "value108" }
    },
    {
      "type": "Feature",
      "geometry": { "type": "Point", "coordinates": [31.30827, -25.02297] },
      "properties": { "name": "value109" }
    },
    {
      "type": "Feature",
      "geometry": { "type": "Point", "coordinates": [31.3081, -25.02289] },
      "properties": { "name": "value110" }
    },
    {
      "type": "Feature",
      "geometry": { "type": "Point", "coordinates": [31.3078, -25.02297] },
      "properties": { "name": "value111" }
    },
    {
      "type": "Feature",
      "geometry": {
        "type": "Point",
        "coordinates": [31.800259999999998, -24.72485]
      },
      "properties": { "name": "value112" }
    },
    {
      "type": "Feature",
      "geometry": {
        "type": "Point",
        "coordinates": [31.307609999999997, -25.022579999999998]
      },
      "properties": { "name": "value113" }
    },
    {
      "type": "Feature",
      "geometry": {
        "type": "Point",
        "coordinates": [31.79702, -24.7256299999999]
      },
      "properties": { "name": "value114" }
    },
    {
      "type": "Feature",
      "geometry": {
        "type": "Point",
        "coordinates": [31.308359999999997, -25.023139999999998]
      },
      "properties": { "name": "value115" }
    },
    {
      "type": "Feature",
      "geometry": {
        "type": "Point",
        "coordinates": [31.7966799999999, -24.726129999999998]
      },
      "properties": { "name": "value116" }
    },
    {
      "type": "Feature",
      "geometry": {
        "type": "Point",
        "coordinates": [31.309590000000004, -25.02351]
      },
      "properties": { "name": "value117" }
    },
    {
      "type": "Feature",
      "geometry": { "type": "Point", "coordinates": [31.79598, -24.72682] },
      "properties": { "name": "value118" }
    },
    {
      "type": "Feature",
      "geometry": {
        "type": "Point",
        "coordinates": [31.30974, -25.0257299999999]
      },
      "properties": { "name": "value119" }
    },
    {
      "type": "Feature",
      "geometry": {
        "type": "Point",
        "coordinates": [31.3104699999999, -25.0282899999999]
      },
      "properties": { "name": "value120" }
    },
    {
      "type": "Feature",
      "geometry": {
        "type": "Point",
        "coordinates": [31.79557, -24.7264899999999]
      },
      "properties": { "name": "value121" }
    },
    {
      "type": "Feature",
      "geometry": { "type": "Point", "coordinates": [31.79484, -24.72588] },
      "properties": { "name": "value122" }
    },
    {
      "type": "Feature",
      "geometry": {
        "type": "Point",
        "coordinates": [31.312459999999998, -25.0305199999999]
      },
      "properties": { "name": "value123" }
    },
    {
      "type": "Feature",
      "geometry": {
        "type": "Point",
        "coordinates": [31.3141399999999, -25.03161]
      },
      "properties": { "name": "value124" }
    },
    {
      "type": "Feature",
      "geometry": {
        "type": "Point",
        "coordinates": [31.314459999999997, -25.032529999999998]
      },
      "properties": { "name": "value125" }
    },
    {
      "type": "Feature",
      "geometry": {
        "type": "Point",
        "coordinates": [31.793259999999997, -24.72277]
      },
      "properties": { "name": "value126" }
    },
    {
      "type": "Feature",
      "geometry": { "type": "Point", "coordinates": [31.31482, -25.03291] },
      "properties": { "name": "value127" }
    },
    {
      "type": "Feature",
      "geometry": {
        "type": "Point",
        "coordinates": [31.7933999999999, -24.7215099999999]
      },
      "properties": { "name": "value128" }
    },
    {
      "type": "Feature",
      "geometry": {
        "type": "Point",
        "coordinates": [31.315179999999998, -25.0333399999999]
      },
      "properties": { "name": "value129" }
    },
    {
      "type": "Feature",
      "geometry": {
        "type": "Point",
        "coordinates": [31.79389, -24.7208599999999]
      },
      "properties": { "name": "value130" }
    },
    {
      "type": "Feature",
      "geometry": {
        "type": "Point",
        "coordinates": [31.315659999999998, -25.0333]
      },
      "properties": { "name": "value131" }
    },
    {
      "type": "Feature",
      "geometry": { "type": "Point", "coordinates": [31.3157, -25.03329] },
      "properties": { "name": "value132" }
    },
    {
      "type": "Feature",
      "geometry": {
        "type": "Point",
        "coordinates": [31.7940499999999, -24.71995]
      },
      "properties": { "name": "value133" }
    },
    {
      "type": "Feature",
      "geometry": { "type": "Point", "coordinates": [31.79438, -24.71929] },
      "properties": { "name": "value134" }
    },
    {
      "type": "Feature",
      "geometry": {
        "type": "Point",
        "coordinates": [31.315590000000004, -25.0333299999999]
      },
      "properties": { "name": "value135" }
    },
    {
      "type": "Feature",
      "geometry": { "type": "Point", "coordinates": [31.79588, -24.71875] },
      "properties": { "name": "value136" }
    },
    {
      "type": "Feature",
      "geometry": { "type": "Point", "coordinates": [31.79787, -24.71752] },
      "properties": { "name": "value137" }
    },
    {
      "type": "Feature",
      "geometry": {
        "type": "Point",
        "coordinates": [31.797829999999998, -24.717579999999998]
      },
      "properties": { "name": "value138" }
    },
    {
      "type": "Feature",
      "geometry": { "type": "Point", "coordinates": [31.31734, -25.0332] },
      "properties": { "name": "value139" }
    },
    {
      "type": "Feature",
      "geometry": {
        "type": "Point",
        "coordinates": [31.79782, -24.7175699999999]
      },
      "properties": { "name": "value140" }
    },
    {
      "type": "Feature",
      "geometry": {
        "type": "Point",
        "coordinates": [31.318590000000004, -25.03293]
      },
      "properties": { "name": "value141" }
    },
    {
      "type": "Feature",
      "geometry": {
        "type": "Point",
        "coordinates": [31.797759999999997, -24.7176699999999]
      },
      "properties": { "name": "value142" }
    },
    {
      "type": "Feature",
      "geometry": {
        "type": "Point",
        "coordinates": [31.318759999999997, -25.031979999999997]
      },
      "properties": { "name": "value143" }
    },
    {
      "type": "Feature",
      "geometry": {
        "type": "Point",
        "coordinates": [31.79917, -24.717129999999997]
      },
      "properties": { "name": "value144" }
    },
    {
      "type": "Feature",
      "geometry": { "type": "Point", "coordinates": [31.32002, -25.03319] },
      "properties": { "name": "value145" }
    },
    {
      "type": "Feature",
      "geometry": {
        "type": "Point",
        "coordinates": [31.3191099999999, -25.0322099999999]
      },
      "properties": { "name": "value146" }
    },
    {
      "type": "Feature",
      "geometry": {
        "type": "Point",
        "coordinates": [31.318609999999996, -25.0303399999999]
      },
      "properties": { "name": "value147" }
    },
    {
      "type": "Feature",
      "geometry": {
        "type": "Point",
        "coordinates": [31.8016299999999, -24.7151]
      },
      "properties": { "name": "value148" }
    },
    {
      "type": "Feature",
      "geometry": {
        "type": "Point",
        "coordinates": [31.316540000000003, -25.027479999999997]
      },
      "properties": { "name": "value149" }
    },
    {
      "type": "Feature",
      "geometry": {
        "type": "Point",
        "coordinates": [31.8027699999999, -24.714779999999998]
      },
      "properties": { "name": "value150" }
    },
    {
      "type": "Feature",
      "geometry": {
        "type": "Point",
        "coordinates": [31.316329999999997, -25.02645]
      },
      "properties": { "name": "value151" }
    },
    {
      "type": "Feature",
      "geometry": {
        "type": "Point",
        "coordinates": [31.8048199999999, -24.7140899999999]
      },
      "properties": { "name": "value152" }
    },
    {
      "type": "Feature",
      "geometry": {
        "type": "Point",
        "coordinates": [31.315559999999998, -25.0259299999999]
      },
      "properties": { "name": "value153" }
    },
    {
      "type": "Feature",
      "geometry": {
        "type": "Point",
        "coordinates": [31.8055799999999, -24.71358]
      },
      "properties": { "name": "value154" }
    },
    {
      "type": "Feature",
      "geometry": {
        "type": "Point",
        "coordinates": [31.314159999999998, -25.02365]
      },
      "properties": { "name": "value155" }
    },
    {
      "type": "Feature",
      "geometry": {
        "type": "Point",
        "coordinates": [31.8073599999999, -24.71265]
      },
      "properties": { "name": "value156" }
    },
    {
      "type": "Feature",
      "geometry": {
        "type": "Point",
        "coordinates": [31.314, -25.0218099999999]
      },
      "properties": { "name": "value157" }
    },
    {
      "type": "Feature",
      "geometry": {
        "type": "Point",
        "coordinates": [31.80902, -24.711779999999997]
      },
      "properties": { "name": "value158" }
    },
    {
      "type": "Feature",
      "geometry": {
        "type": "Point",
        "coordinates": [31.3136599999999, -25.02093]
      },
      "properties": { "name": "value159" }
    },
    {
      "type": "Feature",
      "geometry": { "type": "Point", "coordinates": [31.3137, -25.02075] },
      "properties": { "name": "value160" }
    },
    {
      "type": "Feature",
      "geometry": {
        "type": "Point",
        "coordinates": [31.8147799999999, -24.7068499999999]
      },
      "properties": { "name": "value161" }
    },
    {
      "type": "Feature",
      "geometry": {
        "type": "Point",
        "coordinates": [31.8157299999999, -24.70655]
      },
      "properties": { "name": "value162" }
    },
    {
      "type": "Feature",
      "geometry": {
        "type": "Point",
        "coordinates": [31.31314, -25.019579999999998]
      },
      "properties": { "name": "value163" }
    },
    {
      "type": "Feature",
      "geometry": {
        "type": "Point",
        "coordinates": [31.8156199999999, -24.7062999999999]
      },
      "properties": { "name": "value164" }
    },
    {
      "type": "Feature",
      "geometry": {
        "type": "Point",
        "coordinates": [31.3132799999999, -25.0191]
      },
      "properties": { "name": "value165" }
    },
    {
      "type": "Feature",
      "geometry": {
        "type": "Point",
        "coordinates": [31.815579999999997, -24.70628]
      },
      "properties": { "name": "value166" }
    },
    {
      "type": "Feature",
      "geometry": {
        "type": "Point",
        "coordinates": [31.3123299999999, -25.0196]
      },
      "properties": { "name": "value167" }
    },
    {
      "type": "Feature",
      "geometry": { "type": "Point", "coordinates": [31.80965, -24.70951] },
      "properties": { "name": "value168" }
    },
    {
      "type": "Feature",
      "geometry": {
        "type": "Point",
        "coordinates": [31.3124, -25.0193599999999]
      },
      "properties": { "name": "value169" }
    },
    {
      "type": "Feature",
      "geometry": {
        "type": "Point",
        "coordinates": [31.803390000000004, -24.7118]
      },
      "properties": { "name": "value170" }
    },
    {
      "type": "Feature",
      "geometry": { "type": "Point", "coordinates": [31.3127, -25.01868] },
      "properties": { "name": "value171" }
    },
    {
      "type": "Feature",
      "geometry": {
        "type": "Point",
        "coordinates": [31.3127299999999, -25.0185999999999]
      },
      "properties": { "name": "value172" }
    },
    {
      "type": "Feature",
      "geometry": {
        "type": "Point",
        "coordinates": [31.7937699999999, -24.7145499999999]
      },
      "properties": { "name": "value173" }
    },
    {
      "type": "Feature",
      "geometry": {
        "type": "Point",
        "coordinates": [31.79298, -24.7190499999999]
      },
      "properties": { "name": "value174" }
    },
    {
      "type": "Feature",
      "geometry": {
        "type": "Point",
        "coordinates": [31.7930099999999, -24.71959]
      },
      "properties": { "name": "value175" }
    },
    {
      "type": "Feature",
      "geometry": {
        "type": "Point",
        "coordinates": [31.792709999999996, -24.72171]
      },
      "properties": { "name": "value176" }
    },
    {
      "type": "Feature",
      "geometry": {
        "type": "Point",
        "coordinates": [31.7919799999999, -24.7234799999999]
      },
      "properties": { "name": "value177" }
    },
    {
      "type": "Feature",
      "geometry": {
        "type": "Point",
        "coordinates": [31.7920799999999, -24.723489999999998]
      },
      "properties": { "name": "value178" }
    },
    {
      "type": "Feature",
      "geometry": {
        "type": "Point",
        "coordinates": [31.2941199999999, -25.0273399999999]
      },
      "properties": { "name": "value179" }
    },
    {
      "type": "Feature",
      "geometry": {
        "type": "Point",
        "coordinates": [31.290340000000004, -25.02821]
      },
      "properties": { "name": "value180" }
    },
    {
      "type": "Feature",
      "geometry": {
        "type": "Point",
        "coordinates": [31.79243, -24.7261999999999]
      },
      "properties": { "name": "value181" }
    },
    {
      "type": "Feature",
      "geometry": {
        "type": "Point",
        "coordinates": [31.286459999999998, -25.028579999999998]
      },
      "properties": { "name": "value182" }
    },
    {
      "type": "Feature",
      "geometry": { "type": "Point", "coordinates": [31.79267, -24.72727] },
      "properties": { "name": "value183" }
    },
    {
      "type": "Feature",
      "geometry": {
        "type": "Point",
        "coordinates": [31.2852299999999, -25.03085]
      },
      "properties": { "name": "value184" }
    },
    {
      "type": "Feature",
      "geometry": {
        "type": "Point",
        "coordinates": [31.7928099999999, -24.7276999999999]
      },
      "properties": { "name": "value185" }
    },
    {
      "type": "Feature",
      "geometry": { "type": "Point", "coordinates": [31.28557, -25.03191] },
      "properties": { "name": "value186" }
    },
    {
      "type": "Feature",
      "geometry": {
        "type": "Point",
        "coordinates": [31.793359999999996, -24.72776]
      },
      "properties": { "name": "value187" }
    },
    {
      "type": "Feature",
      "geometry": {
        "type": "Point",
        "coordinates": [31.285429999999998, -25.0321]
      },
      "properties": { "name": "value188" }
    },
    {
      "type": "Feature",
      "geometry": {
        "type": "Point",
        "coordinates": [31.7938499999999, -24.7276899999999]
      },
      "properties": { "name": "value189" }
    },
    {
      "type": "Feature",
      "geometry": { "type": "Point", "coordinates": [31.28473, -25.03265] },
      "properties": { "name": "value190" }
    },
    {
      "type": "Feature",
      "geometry": {
        "type": "Point",
        "coordinates": [31.7934799999999, -24.7279599999999]
      },
      "properties": { "name": "value191" }
    },
    {
      "type": "Feature",
      "geometry": {
        "type": "Point",
        "coordinates": [31.28453, -25.0327899999999]
      },
      "properties": { "name": "value192" }
    },
    {
      "type": "Feature",
      "geometry": {
        "type": "Point",
        "coordinates": [31.2846499999999, -25.033079999999998]
      },
      "properties": { "name": "value193" }
    },
    {
      "type": "Feature",
      "geometry": {
        "type": "Point",
        "coordinates": [31.2851199999999, -25.03375]
      },
      "properties": { "name": "value194" }
    },
    {
      "type": "Feature",
      "geometry": {
        "type": "Point",
        "coordinates": [31.7946999999999, -24.7271199999999]
      },
      "properties": { "name": "value195" }
    },
    {
      "type": "Feature",
      "geometry": {
        "type": "Point",
        "coordinates": [31.28517, -25.0340799999999]
      },
      "properties": { "name": "value196" }
    },
    {
      "type": "Feature",
      "geometry": {
        "type": "Point",
        "coordinates": [31.2853999999999, -25.03461]
      },
      "properties": { "name": "value197" }
    },
    {
      "type": "Feature",
      "geometry": {
        "type": "Point",
        "coordinates": [31.2860699999999, -25.03499]
      },
      "properties": { "name": "value198" }
    },
    {
      "type": "Feature",
      "geometry": {
        "type": "Point",
        "coordinates": [31.286140000000003, -25.03497]
      },
      "properties": { "name": "value199" }
    },
    {
      "type": "Feature",
      "geometry": {
        "type": "Point",
        "coordinates": [31.798790000000004, -24.7264799999999]
      },
      "properties": { "name": "value200" }
    },
    {
      "type": "Feature",
      "geometry": {
        "type": "Point",
        "coordinates": [31.2861599999999, -25.035]
      },
      "properties": { "name": "value201" }
    },
    {
      "type": "Feature",
      "geometry": { "type": "Point", "coordinates": [31.79849, -24.72654] },
      "properties": { "name": "value202" }
    },
    {
      "type": "Feature",
      "geometry": { "type": "Point", "coordinates": [31.2862, -25.03511] },
      "properties": { "name": "value203" }
    },
    {
      "type": "Feature",
      "geometry": {
        "type": "Point",
        "coordinates": [31.286209999999997, -25.0350299999999]
      },
      "properties": { "name": "value204" }
    },
    {
      "type": "Feature",
      "geometry": { "type": "Point", "coordinates": [31.80019, -24.72491] },
      "properties": { "name": "value205" }
    },
    {
      "type": "Feature",
      "geometry": {
        "type": "Point",
        "coordinates": [31.8017399999999, -24.7240499999999]
      },
      "properties": { "name": "value206" }
    },
    {
      "type": "Feature",
      "geometry": {
        "type": "Point",
        "coordinates": [31.289140000000003, -25.03818]
      },
      "properties": { "name": "value207" }
    },
    {
      "type": "Feature",
      "geometry": {
        "type": "Point",
        "coordinates": [31.289309999999997, -25.03854]
      },
      "properties": { "name": "value208" }
    },
    {
      "type": "Feature",
      "geometry": {
        "type": "Point",
        "coordinates": [31.80319, -24.7232799999999]
      },
      "properties": { "name": "value209" }
    },
    {
      "type": "Feature",
      "geometry": { "type": "Point", "coordinates": [31.28975, -25.03949] },
      "properties": { "name": "value210" }
    },
    {
      "type": "Feature",
      "geometry": {
        "type": "Point",
        "coordinates": [31.8032499999999, -24.72336]
      },
      "properties": { "name": "value211" }
    },
    {
      "type": "Feature",
      "geometry": {
        "type": "Point",
        "coordinates": [31.28978, -25.0400099999999]
      },
      "properties": { "name": "value212" }
    },
    {
      "type": "Feature",
      "geometry": {
        "type": "Point",
        "coordinates": [31.290309999999998, -25.0403699999999]
      },
      "properties": { "name": "value213" }
    },
    {
      "type": "Feature",
      "geometry": {
        "type": "Point",
        "coordinates": [31.29175, -25.040329999999997]
      },
      "properties": { "name": "value214" }
    },
    {
      "type": "Feature",
      "geometry": { "type": "Point", "coordinates": [31.80322, -24.72276] },
      "properties": { "name": "value215" }
    },
    {
      "type": "Feature",
      "geometry": {
        "type": "Point",
        "coordinates": [31.29445, -25.039839999999998]
      },
      "properties": { "name": "value216" }
    },
    {
      "type": "Feature",
      "geometry": {
        "type": "Point",
        "coordinates": [31.2984499999999, -25.03941]
      },
      "properties": { "name": "value217" }
    },
    {
      "type": "Feature",
      "geometry": {
        "type": "Point",
        "coordinates": [31.2992199999999, -25.04025]
      },
      "properties": { "name": "value218" }
    },
    {
      "type": "Feature",
      "geometry": {
        "type": "Point",
        "coordinates": [31.299509999999998, -25.04063]
      },
      "properties": { "name": "value219" }
    },
    {
      "type": "Feature",
      "geometry": {
        "type": "Point",
        "coordinates": [31.804240000000004, -24.7224]
      },
      "properties": { "name": "value220" }
    },
    {
      "type": "Feature",
      "geometry": {
        "type": "Point",
        "coordinates": [31.3000499999999, -25.04119]
      },
      "properties": { "name": "value221" }
    },
    {
      "type": "Feature",
      "geometry": {
        "type": "Point",
        "coordinates": [31.804609999999997, -24.72214]
      },
      "properties": { "name": "value222" }
    },
    {
      "type": "Feature",
      "geometry": {
        "type": "Point",
        "coordinates": [31.30087, -25.0414999999999]
      },
      "properties": { "name": "value223" }
    },
    {
      "type": "Feature",
      "geometry": {
        "type": "Point",
        "coordinates": [31.3013499999999, -25.0417099999999]
      },
      "properties": { "name": "value224" }
    },
    {
      "type": "Feature",
      "geometry": { "type": "Point", "coordinates": [31.30228, -25.04126] },
      "properties": { "name": "value225" }
    },
    {
      "type": "Feature",
      "geometry": {
        "type": "Point",
        "coordinates": [31.8075399999999, -24.72045]
      },
      "properties": { "name": "value226" }
    },
    {
      "type": "Feature",
      "geometry": {
        "type": "Point",
        "coordinates": [31.30347, -25.0408599999999]
      },
      "properties": { "name": "value227" }
    },
    {
      "type": "Feature",
      "geometry": {
        "type": "Point",
        "coordinates": [31.80797, -24.720229999999997]
      },
      "properties": { "name": "value228" }
    },
    {
      "type": "Feature",
      "geometry": {
        "type": "Point",
        "coordinates": [31.302709999999998, -25.039]
      },
      "properties": { "name": "value229" }
    },
    {
      "type": "Feature",
      "geometry": {
        "type": "Point",
        "coordinates": [31.8087799999999, -24.72007]
      },
      "properties": { "name": "value230" }
    },
    {
      "type": "Feature",
      "geometry": { "type": "Point", "coordinates": [31.30067, -25.03689] },
      "properties": { "name": "value231" }
    },
    {
      "type": "Feature",
      "geometry": { "type": "Point", "coordinates": [31.80917, -24.71985] },
      "properties": { "name": "value232" }
    },
    {
      "type": "Feature",
      "geometry": {
        "type": "Point",
        "coordinates": [31.29839, -25.034589999999998]
      },
      "properties": { "name": "value233" }
    },
    {
      "type": "Feature",
      "geometry": {
        "type": "Point",
        "coordinates": [31.8118699999999, -24.71955]
      },
      "properties": { "name": "value234" }
    },
    {
      "type": "Feature",
      "geometry": {
        "type": "Point",
        "coordinates": [31.29699, -25.0337099999999]
      },
      "properties": { "name": "value235" }
    },
    {
      "type": "Feature",
      "geometry": {
        "type": "Point",
        "coordinates": [31.2948099999999, -25.0332599999999]
      },
      "properties": { "name": "value236" }
    },
    {
      "type": "Feature",
      "geometry": {
        "type": "Point",
        "coordinates": [31.2944, -25.0331499999999]
      },
      "properties": { "name": "value237" }
    },
    {
      "type": "Feature",
      "geometry": {
        "type": "Point",
        "coordinates": [31.2917899999999, -25.0345499999999]
      },
      "properties": { "name": "value238" }
    },
    {
      "type": "Feature",
      "geometry": {
        "type": "Point",
        "coordinates": [31.8149699999999, -24.72176]
      },
      "properties": { "name": "value239" }
    },
    {
      "type": "Feature",
      "geometry": { "type": "Point", "coordinates": [31.29125, -25.03432] },
      "properties": { "name": "value240" }
    },
    {
      "type": "Feature",
      "geometry": {
        "type": "Point",
        "coordinates": [31.811740000000004, -24.7285299999999]
      },
      "properties": { "name": "value241" }
    },
    {
      "type": "Feature",
      "geometry": {
        "type": "Point",
        "coordinates": [31.28762, -25.036089999999998]
      },
      "properties": { "name": "value242" }
    },
    {
      "type": "Feature",
      "geometry": { "type": "Point", "coordinates": [31.80805, -24.73186] },
      "properties": { "name": "value243" }
    },
    {
      "type": "Feature",
      "geometry": {
        "type": "Point",
        "coordinates": [31.2860799999999, -25.03497]
      },
      "properties": { "name": "value244" }
    },
    {
      "type": "Feature",
      "geometry": {
        "type": "Point",
        "coordinates": [31.801509999999997, -24.7352999999999]
      },
      "properties": { "name": "value245" }
    },
    {
      "type": "Feature",
      "geometry": {
        "type": "Point",
        "coordinates": [31.2855999999999, -25.0345599999999]
      },
      "properties": { "name": "value246" }
    },
    {
      "type": "Feature",
      "geometry": {
        "type": "Point",
        "coordinates": [31.798990000000003, -24.7353799999999]
      },
      "properties": { "name": "value247" }
    },
    {
      "type": "Feature",
      "geometry": {
        "type": "Point",
        "coordinates": [31.285629999999998, -25.03452]
      },
      "properties": { "name": "value248" }
    },
    {
      "type": "Feature",
      "geometry": { "type": "Point", "coordinates": [31.79744, -24.73551] },
      "properties": { "name": "value249" }
    },
    {
      "type": "Feature",
      "geometry": { "type": "Point", "coordinates": [31.28479, -25.03432] },
      "properties": { "name": "value250" }
    },
    {
      "type": "Feature",
      "geometry": { "type": "Point", "coordinates": [31.79607, -24.73607] },
      "properties": { "name": "value251" }
    },
    {
      "type": "Feature",
      "geometry": { "type": "Point", "coordinates": [31.28285, -25.03412] },
      "properties": { "name": "value252" }
    },
    {
      "type": "Feature",
      "geometry": {
        "type": "Point",
        "coordinates": [31.79577, -24.735429999999997]
      },
      "properties": { "name": "value253" }
    },
    {
      "type": "Feature",
      "geometry": { "type": "Point", "coordinates": [31.2819, -25.03415] },
      "properties": { "name": "value254" }
    },
    {
      "type": "Feature",
      "geometry": {
        "type": "Point",
        "coordinates": [31.7938399999999, -24.735529999999997]
      },
      "properties": { "name": "value255" }
    },
    {
      "type": "Feature",
      "geometry": {
        "type": "Point",
        "coordinates": [31.28143, -25.034879999999998]
      },
      "properties": { "name": "value256" }
    },
    {
      "type": "Feature",
      "geometry": {
        "type": "Point",
        "coordinates": [31.2809899999999, -25.03506]
      },
      "properties": { "name": "value257" }
    },
    {
      "type": "Feature",
      "geometry": {
        "type": "Point",
        "coordinates": [31.7912399999999, -24.7376399999999]
      },
      "properties": { "name": "value258" }
    },
    {
      "type": "Feature",
      "geometry": {
        "type": "Point",
        "coordinates": [31.27778, -25.0348599999999]
      },
      "properties": { "name": "value259" }
    },
    {
      "type": "Feature",
      "geometry": {
        "type": "Point",
        "coordinates": [31.7917899999999, -24.73509]
      },
      "properties": { "name": "value260" }
    },
    {
      "type": "Feature",
      "geometry": {
        "type": "Point",
        "coordinates": [31.27859, -25.0341799999999]
      },
      "properties": { "name": "value261" }
    },
    {
      "type": "Feature",
      "geometry": {
        "type": "Point",
        "coordinates": [31.7932899999999, -24.7339699999999]
      },
      "properties": { "name": "value262" }
    },
    {
      "type": "Feature",
      "geometry": {
        "type": "Point",
        "coordinates": [31.27832, -25.0331499999999]
      },
      "properties": { "name": "value263" }
    },
    {
      "type": "Feature",
      "geometry": {
        "type": "Point",
        "coordinates": [31.278809999999996, -25.0325899999999]
      },
      "properties": { "name": "value264" }
    },
    {
      "type": "Feature",
      "geometry": {
        "type": "Point",
        "coordinates": [31.2775399999999, -25.03153]
      },
      "properties": { "name": "value265" }
    },
    {
      "type": "Feature",
      "geometry": {
        "type": "Point",
        "coordinates": [31.276259999999997, -25.031779999999998]
      },
      "properties": { "name": "value266" }
    },
    {
      "type": "Feature",
      "geometry": { "type": "Point", "coordinates": [31.27605, -25.03205] },
      "properties": { "name": "value267" }
    },
    {
      "type": "Feature",
      "geometry": { "type": "Point", "coordinates": [31.2755, -25.03209] },
      "properties": { "name": "value268" }
    },
    {
      "type": "Feature",
      "geometry": {
        "type": "Point",
        "coordinates": [31.275009999999998, -25.03192]
      },
      "properties": { "name": "value269" }
    },
    {
      "type": "Feature",
      "geometry": { "type": "Point", "coordinates": [31.79295, -24.72889] },
      "properties": { "name": "value270" }
    },
    {
      "type": "Feature",
      "geometry": {
        "type": "Point",
        "coordinates": [31.27354, -25.031979999999997]
      },
      "properties": { "name": "value271" }
    },
    {
      "type": "Feature",
      "geometry": {
        "type": "Point",
        "coordinates": [31.2729299999999, -25.031779999999998]
      },
      "properties": { "name": "value272" }
    },
    {
      "type": "Feature",
      "geometry": {
        "type": "Point",
        "coordinates": [31.273059999999997, -25.03196]
      },
      "properties": { "name": "value273" }
    },
    {
      "type": "Feature",
      "geometry": { "type": "Point", "coordinates": [31.27307, -25.03209] },
      "properties": { "name": "value274" }
    },
    {
      "type": "Feature",
      "geometry": {
        "type": "Point",
        "coordinates": [31.792140000000003, -24.7284]
      },
      "properties": { "name": "value275" }
    },
    {
      "type": "Feature",
      "geometry": {
        "type": "Point",
        "coordinates": [31.79192, -24.7284399999999]
      },
      "properties": { "name": "value276" }
    },
    {
      "type": "Feature",
      "geometry": {
        "type": "Point",
        "coordinates": [31.271859999999997, -25.031589999999998]
      },
      "properties": { "name": "value277" }
    },
    {
      "type": "Feature",
      "geometry": {
        "type": "Point",
        "coordinates": [31.792109999999997, -24.72813]
      },
      "properties": { "name": "value278" }
    },
    {
      "type": "Feature",
      "geometry": {
        "type": "Point",
        "coordinates": [31.269379999999998, -25.0309199999999]
      },
      "properties": { "name": "value279" }
    },
    {
      "type": "Feature",
      "geometry": {
        "type": "Point",
        "coordinates": [31.792759999999998, -24.7274999999999]
      },
      "properties": { "name": "value280" }
    },
    {
      "type": "Feature",
      "geometry": { "type": "Point", "coordinates": [31.26877, -25.03098] },
      "properties": { "name": "value281" }
    },
    {
      "type": "Feature",
      "geometry": {
        "type": "Point",
        "coordinates": [31.2661, -25.0311799999999]
      },
      "properties": { "name": "value282" }
    },
    {
      "type": "Feature",
      "geometry": {
        "type": "Point",
        "coordinates": [31.26455, -25.031589999999998]
      },
      "properties": { "name": "value283" }
    },
    {
      "type": "Feature",
      "geometry": {
        "type": "Point",
        "coordinates": [31.79383, -24.726779999999998]
      },
      "properties": { "name": "value284" }
    },
    {
      "type": "Feature",
      "geometry": {
        "type": "Point",
        "coordinates": [31.2645899999999, -25.031589999999998]
      },
      "properties": { "name": "value285" }
    },
    {
      "type": "Feature",
      "geometry": {
        "type": "Point",
        "coordinates": [31.2646599999999, -25.0315599999999]
      },
      "properties": { "name": "value286" }
    },
    {
      "type": "Feature",
      "geometry": { "type": "Point", "coordinates": [31.26455, -25.03151] },
      "properties": { "name": "value287" }
    },
    {
      "type": "Feature",
      "geometry": { "type": "Point", "coordinates": [31.2639, -25.03151] },
      "properties": { "name": "value288" }
    },
    {
      "type": "Feature",
      "geometry": {
        "type": "Point",
        "coordinates": [31.7935799999999, -24.7257199999999]
      },
      "properties": { "name": "value289" }
    },
    {
      "type": "Feature",
      "geometry": {
        "type": "Point",
        "coordinates": [31.26319, -25.0313799999999]
      },
      "properties": { "name": "value290" }
    },
    {
      "type": "Feature",
      "geometry": { "type": "Point", "coordinates": [31.79332, -24.72567] },
      "properties": { "name": "value291" }
    },
    {
      "type": "Feature",
      "geometry": {
        "type": "Point",
        "coordinates": [31.2625899999999, -25.0312899999999]
      },
      "properties": { "name": "value292" }
    },
    {
      "type": "Feature",
      "geometry": {
        "type": "Point",
        "coordinates": [31.261459999999996, -25.0303399999999]
      },
      "properties": { "name": "value293" }
    },
    {
      "type": "Feature",
      "geometry": {
        "type": "Point",
        "coordinates": [31.2606499999999, -25.02915]
      },
      "properties": { "name": "value294" }
    },
    {
      "type": "Feature",
      "geometry": {
        "type": "Point",
        "coordinates": [31.7926399999999, -24.7258299999999]
      },
      "properties": { "name": "value295" }
    },
    {
      "type": "Feature",
      "geometry": {
        "type": "Point",
        "coordinates": [31.2596099999999, -25.0283799999999]
      },
      "properties": { "name": "value296" }
    },
    {
      "type": "Feature",
      "geometry": {
        "type": "Point",
        "coordinates": [31.792659999999998, -24.72587]
      },
      "properties": { "name": "value297" }
    },
    {
      "type": "Feature",
      "geometry": {
        "type": "Point",
        "coordinates": [31.259559999999997, -25.027379999999997]
      },
      "properties": { "name": "value298" }
    },
    {
      "type": "Feature",
      "geometry": { "type": "Point", "coordinates": [31.2601, -25.02712] },
      "properties": { "name": "value299" }
    },
    {
      "type": "Feature",
      "geometry": {
        "type": "Point",
        "coordinates": [31.260479999999998, -25.0268]
      },
      "properties": { "name": "value300" }
    },
    {
      "type": "Feature",
      "geometry": {
        "type": "Point",
        "coordinates": [31.2608199999999, -25.0264899999999]
      },
      "properties": { "name": "value301" }
    },
    {
      "type": "Feature",
      "geometry": {
        "type": "Point",
        "coordinates": [31.7927299999999, -24.725839999999998]
      },
      "properties": { "name": "value302" }
    },
    {
      "type": "Feature",
      "geometry": {
        "type": "Point",
        "coordinates": [31.261029999999998, -25.0261999999999]
      },
      "properties": { "name": "value303" }
    },
    {
      "type": "Feature",
      "geometry": {
        "type": "Point",
        "coordinates": [31.2609199999999, -25.02569]
      },
      "properties": { "name": "value304" }
    },
    {
      "type": "Feature",
      "geometry": {
        "type": "Point",
        "coordinates": [31.261440000000004, -25.0280999999999]
      },
      "properties": { "name": "value305" }
    },
    {
      "type": "Feature",
      "geometry": {
        "type": "Point",
        "coordinates": [31.7931199999999, -24.72655]
      },
      "properties": { "name": "value306" }
    },
    {
      "type": "Feature",
      "geometry": { "type": "Point", "coordinates": [31.79334, -24.72605] },
      "properties": { "name": "value307" }
    },
    {
      "type": "Feature",
      "geometry": {
        "type": "Point",
        "coordinates": [31.793709999999997, -24.72546]
      },
      "properties": { "name": "value308" }
    },
    {
      "type": "Feature",
      "geometry": {
        "type": "Point",
        "coordinates": [31.7933899999999, -24.72523]
      },
      "properties": { "name": "value309" }
    },
    {
      "type": "Feature",
      "geometry": { "type": "Point", "coordinates": [31.2608, -25.02261] },
      "properties": { "name": "value310" }
    },
    {
      "type": "Feature",
      "geometry": {
        "type": "Point",
        "coordinates": [31.2622299999999, -25.02582]
      },
      "properties": { "name": "value311" }
    },
    {
      "type": "Feature",
      "geometry": {
        "type": "Point",
        "coordinates": [31.793029999999998, -24.72428]
      },
      "properties": { "name": "value312" }
    },
    {
      "type": "Feature",
      "geometry": {
        "type": "Point",
        "coordinates": [31.7928, -24.7242099999999]
      },
      "properties": { "name": "value313" }
    },
    {
      "type": "Feature",
      "geometry": { "type": "Point", "coordinates": [31.26275, -25.02661] },
      "properties": { "name": "value314" }
    },
    {
      "type": "Feature",
      "geometry": {
        "type": "Point",
        "coordinates": [31.26362, -25.0265999999999]
      },
      "properties": { "name": "value315" }
    },
    {
      "type": "Feature",
      "geometry": { "type": "Point", "coordinates": [31.2652, -25.02994] },
      "properties": { "name": "value316" }
    },
    {
      "type": "Feature",
      "geometry": {
        "type": "Point",
        "coordinates": [31.266479999999998, -25.0316399999999]
      },
      "properties": { "name": "value317" }
    },
    {
      "type": "Feature",
      "geometry": {
        "type": "Point",
        "coordinates": [31.2664399999999, -25.033279999999998]
      },
      "properties": { "name": "value318" }
    },
    {
      "type": "Feature",
      "geometry": {
        "type": "Point",
        "coordinates": [31.7924599999999, -24.72372]
      },
      "properties": { "name": "value319" }
    },
    {
      "type": "Feature",
      "geometry": {
        "type": "Point",
        "coordinates": [31.266779999999997, -25.03491]
      },
      "properties": { "name": "value320" }
    },
    {
      "type": "Feature",
      "geometry": {
        "type": "Point",
        "coordinates": [31.79294, -24.7229099999999]
      },
      "properties": { "name": "value321" }
    },
    {
      "type": "Feature",
      "geometry": {
        "type": "Point",
        "coordinates": [31.2673799999999, -25.0360699999999]
      },
      "properties": { "name": "value322" }
    },
    {
      "type": "Feature",
      "geometry": { "type": "Point", "coordinates": [31.79392, -24.72152] },
      "properties": { "name": "value323" }
    },
    {
      "type": "Feature",
      "geometry": {
        "type": "Point",
        "coordinates": [31.26762, -25.0369899999999]
      },
      "properties": { "name": "value324" }
    },
    {
      "type": "Feature",
      "geometry": {
        "type": "Point",
        "coordinates": [31.79547, -24.7201899999999]
      },
      "properties": { "name": "value325" }
    },
    {
      "type": "Feature",
      "geometry": {
        "type": "Point",
        "coordinates": [31.2673899999999, -25.038529999999998]
      },
      "properties": { "name": "value326" }
    },
    {
      "type": "Feature",
      "geometry": {
        "type": "Point",
        "coordinates": [31.2681, -25.0394499999999]
      },
      "properties": { "name": "value327" }
    },
    {
      "type": "Feature",
      "geometry": {
        "type": "Point",
        "coordinates": [31.26913, -25.0395399999999]
      },
      "properties": { "name": "value328" }
    },
    {
      "type": "Feature",
      "geometry": {
        "type": "Point",
        "coordinates": [31.797590000000003, -24.7171999999999]
      },
      "properties": { "name": "value329" }
    },
    {
      "type": "Feature",
      "geometry": {
        "type": "Point",
        "coordinates": [31.270529999999997, -25.04045]
      },
      "properties": { "name": "value330" }
    },
    {
      "type": "Feature",
      "geometry": {
        "type": "Point",
        "coordinates": [31.2698199999999, -25.0420599999999]
      },
      "properties": { "name": "value331" }
    },
    {
      "type": "Feature",
      "geometry": {
        "type": "Point",
        "coordinates": [31.268729999999998, -25.0435899999999]
      },
      "properties": { "name": "value332" }
    },
    {
      "type": "Feature",
      "geometry": {
        "type": "Point",
        "coordinates": [31.2684399999999, -25.0441499999999]
      },
      "properties": { "name": "value333" }
    },
    {
      "type": "Feature",
      "geometry": {
        "type": "Point",
        "coordinates": [31.8012, -24.714579999999998]
      },
      "properties": { "name": "value334" }
    },
    {
      "type": "Feature",
      "geometry": { "type": "Point", "coordinates": [31.26874, -25.04364] },
      "properties": { "name": "value335" }
    },
    {
      "type": "Feature",
      "geometry": { "type": "Point", "coordinates": [31.26878, -25.04364] },
      "properties": { "name": "value336" }
    },
    {
      "type": "Feature",
      "geometry": {
        "type": "Point",
        "coordinates": [31.268909999999998, -25.04327]
      },
      "properties": { "name": "value337" }
    },
    {
      "type": "Feature",
      "geometry": {
        "type": "Point",
        "coordinates": [31.2687999999999, -25.0435699999999]
      },
      "properties": { "name": "value338" }
    },
    {
      "type": "Feature",
      "geometry": {
        "type": "Point",
        "coordinates": [31.2685999999999, -25.0438499999999]
      },
      "properties": { "name": "value339" }
    },
    {
      "type": "Feature",
      "geometry": {
        "type": "Point",
        "coordinates": [31.2683199999999, -25.04362]
      },
      "properties": { "name": "value340" }
    },
    {
      "type": "Feature",
      "geometry": {
        "type": "Point",
        "coordinates": [31.268009999999997, -25.0451]
      },
      "properties": { "name": "value341" }
    },
    {
      "type": "Feature",
      "geometry": {
        "type": "Point",
        "coordinates": [31.266779999999997, -25.04617]
      },
      "properties": { "name": "value342" }
    },
    {
      "type": "Feature",
      "geometry": {
        "type": "Point",
        "coordinates": [31.267329999999998, -25.0456299999999]
      },
      "properties": { "name": "value343" }
    },
    {
      "type": "Feature",
      "geometry": {
        "type": "Point",
        "coordinates": [31.267509999999998, -25.04532]
      },
      "properties": { "name": "value344" }
    },
    {
      "type": "Feature",
      "geometry": { "type": "Point", "coordinates": [31.26728, -25.04523] },
      "properties": { "name": "value345" }
    },
    {
      "type": "Feature",
      "geometry": {
        "type": "Point",
        "coordinates": [31.26697, -25.0451699999999]
      },
      "properties": { "name": "value346" }
    },
    {
      "type": "Feature",
      "geometry": {
        "type": "Point",
        "coordinates": [31.2667299999999, -25.04465]
      },
      "properties": { "name": "value347" }
    },
    {
      "type": "Feature",
      "geometry": {
        "type": "Point",
        "coordinates": [31.266109999999998, -25.0438499999999]
      },
      "properties": { "name": "value348" }
    },
    {
      "type": "Feature",
      "geometry": { "type": "Point", "coordinates": [31.26499, -25.04212] },
      "properties": { "name": "value349" }
    },
    {
      "type": "Feature",
      "geometry": {
        "type": "Point",
        "coordinates": [31.2654999999999, -25.04221]
      },
      "properties": { "name": "value350" }
    },
    {
      "type": "Feature",
      "geometry": {
        "type": "Point",
        "coordinates": [31.840290000000003, -24.6944]
      },
      "properties": { "name": "value351" }
    },
    {
      "type": "Feature",
      "geometry": { "type": "Point", "coordinates": [31.26142, -25.03957] },
      "properties": { "name": "value352" }
    },
    {
      "type": "Feature",
      "geometry": {
        "type": "Point",
        "coordinates": [31.8400399999999, -24.69441]
      },
      "properties": { "name": "value353" }
    },
    {
      "type": "Feature",
      "geometry": {
        "type": "Point",
        "coordinates": [31.259809999999998, -25.037779999999998]
      },
      "properties": { "name": "value354" }
    },
    {
      "type": "Feature",
      "geometry": { "type": "Point", "coordinates": [31.25824, -25.03669] },
      "properties": { "name": "value355" }
    },
    {
      "type": "Feature",
      "geometry": {
        "type": "Point",
        "coordinates": [31.2569599999999, -25.0365299999999]
      },
      "properties": { "name": "value356" }
    },
    {
      "type": "Feature",
      "geometry": {
        "type": "Point",
        "coordinates": [31.83755, -24.6988699999999]
      },
      "properties": { "name": "value357" }
    },
    {
      "type": "Feature",
      "geometry": {
        "type": "Point",
        "coordinates": [31.25625, -25.037779999999998]
      },
      "properties": { "name": "value358" }
    },
    {
      "type": "Feature",
      "geometry": {
        "type": "Point",
        "coordinates": [31.8401999999999, -24.70054]
      },
      "properties": { "name": "value359" }
    },
    {
      "type": "Feature",
      "geometry": {
        "type": "Point",
        "coordinates": [31.25822, -25.0404899999999]
      },
      "properties": { "name": "value360" }
    },
    {
      "type": "Feature",
      "geometry": {
        "type": "Point",
        "coordinates": [31.259359999999997, -25.04191]
      },
      "properties": { "name": "value361" }
    },
    {
      "type": "Feature",
      "geometry": {
        "type": "Point",
        "coordinates": [31.2603599999999, -25.04326]
      },
      "properties": { "name": "value362" }
    },
    {
      "type": "Feature",
      "geometry": {
        "type": "Point",
        "coordinates": [31.8414499999999, -24.7061899999999]
      },
      "properties": { "name": "value363" }
    },
    {
      "type": "Feature",
      "geometry": {
        "type": "Point",
        "coordinates": [31.259459999999997, -25.04456]
      },
      "properties": { "name": "value364" }
    },
    {
      "type": "Feature",
      "geometry": { "type": "Point", "coordinates": [31.83967, -24.71554] },
      "properties": { "name": "value365" }
    },
    {
      "type": "Feature",
      "geometry": {
        "type": "Point",
        "coordinates": [31.260559999999998, -25.04641]
      },
      "properties": { "name": "value366" }
    },
    {
      "type": "Feature",
      "geometry": {
        "type": "Point",
        "coordinates": [31.261229999999998, -25.0479999999999]
      },
      "properties": { "name": "value367" }
    },
    {
      "type": "Feature",
      "geometry": { "type": "Point", "coordinates": [31.26209, -25.05009] },
      "properties": { "name": "value368" }
    },
    {
      "type": "Feature",
      "geometry": {
        "type": "Point",
        "coordinates": [31.2612899999999, -25.050929999999997]
      },
      "properties": { "name": "value369" }
    },
    {
      "type": "Feature",
      "geometry": {
        "type": "Point",
        "coordinates": [31.2546399999999, -25.04909]
      },
      "properties": { "name": "value370" }
    },
    {
      "type": "Feature",
      "geometry": {
        "type": "Point",
        "coordinates": [31.2534199999999, -25.04974]
      },
      "properties": { "name": "value371" }
    },
    {
      "type": "Feature",
      "geometry": {
        "type": "Point",
        "coordinates": [31.2535899999999, -25.05092]
      },
      "properties": { "name": "value372" }
    },
    {
      "type": "Feature",
      "geometry": {
        "type": "Point",
        "coordinates": [31.818690000000004, -24.7192599999999]
      },
      "properties": { "name": "value373" }
    },
    {
      "type": "Feature",
      "geometry": {
        "type": "Point",
        "coordinates": [31.25315, -25.0520099999999]
      },
      "properties": { "name": "value374" }
    },
    {
      "type": "Feature",
      "geometry": {
        "type": "Point",
        "coordinates": [31.253159999999998, -25.05198]
      },
      "properties": { "name": "value375" }
    },
    {
      "type": "Feature",
      "geometry": { "type": "Point", "coordinates": [31.81775, -24.71796] },
      "properties": { "name": "value376" }
    },
    {
      "type": "Feature",
      "geometry": {
        "type": "Point",
        "coordinates": [31.2527, -25.0522899999999]
      },
      "properties": { "name": "value377" }
    },
    {
      "type": "Feature",
      "geometry": {
        "type": "Point",
        "coordinates": [31.2512599999999, -25.0530499999999]
      },
      "properties": { "name": "value378" }
    },
    {
      "type": "Feature",
      "geometry": {
        "type": "Point",
        "coordinates": [31.8160899999999, -24.7181199999999]
      },
      "properties": { "name": "value379" }
    },
    {
      "type": "Feature",
      "geometry": { "type": "Point", "coordinates": [31.24895, -25.05396] },
      "properties": { "name": "value380" }
    },
    {
      "type": "Feature",
      "geometry": {
        "type": "Point",
        "coordinates": [31.8156399999999, -24.7199099999999]
      },
      "properties": { "name": "value381" }
    },
    {
      "type": "Feature",
      "geometry": {
        "type": "Point",
        "coordinates": [31.249059999999997, -25.0543799999999]
      },
      "properties": { "name": "value382" }
    },
    {
      "type": "Feature",
      "geometry": {
        "type": "Point",
        "coordinates": [31.815309999999997, -24.7192599999999]
      },
      "properties": { "name": "value383" }
    },
    {
      "type": "Feature",
      "geometry": {
        "type": "Point",
        "coordinates": [31.2487199999999, -25.05552]
      },
      "properties": { "name": "value384" }
    },
    {
      "type": "Feature",
      "geometry": {
        "type": "Point",
        "coordinates": [31.8080099999999, -24.72475]
      },
      "properties": { "name": "value385" }
    },
    {
      "type": "Feature",
      "geometry": {
        "type": "Point",
        "coordinates": [31.249159999999996, -25.0563]
      },
      "properties": { "name": "value386" }
    },
    {
      "type": "Feature",
      "geometry": {
        "type": "Point",
        "coordinates": [31.809109999999997, -24.72673]
      },
      "properties": { "name": "value387" }
    },
    {
      "type": "Feature",
      "geometry": {
        "type": "Point",
        "coordinates": [31.24912, -25.0567199999999]
      },
      "properties": { "name": "value388" }
    },
    {
      "type": "Feature",
      "geometry": {
        "type": "Point",
        "coordinates": [31.249209999999998, -25.05751]
      },
      "properties": { "name": "value389" }
    },
    {
      "type": "Feature",
      "geometry": { "type": "Point", "coordinates": [31.24914, -25.05732] },
      "properties": { "name": "value390" }
    },
    {
      "type": "Feature",
      "geometry": {
        "type": "Point",
        "coordinates": [31.2488899999999, -25.05685]
      },
      "properties": { "name": "value391" }
    },
    {
      "type": "Feature",
      "geometry": {
        "type": "Point",
        "coordinates": [31.8030499999999, -24.73317]
      },
      "properties": { "name": "value392" }
    },
    {
      "type": "Feature",
      "geometry": { "type": "Point", "coordinates": [31.24832, -25.05725] },
      "properties": { "name": "value393" }
    },
    {
      "type": "Feature",
      "geometry": {
        "type": "Point",
        "coordinates": [31.799640000000004, -24.73402]
      },
      "properties": { "name": "value394" }
    },
    {
      "type": "Feature",
      "geometry": {
        "type": "Point",
        "coordinates": [31.247759999999996, -25.05752]
      },
      "properties": { "name": "value395" }
    },
    {
      "type": "Feature",
      "geometry": {
        "type": "Point",
        "coordinates": [31.79768, -24.7352799999999]
      },
      "properties": { "name": "value396" }
    },
    {
      "type": "Feature",
      "geometry": {
        "type": "Point",
        "coordinates": [31.2475799999999, -25.05826]
      },
      "properties": { "name": "value397" }
    },
    {
      "type": "Feature",
      "geometry": {
        "type": "Point",
        "coordinates": [31.797290000000004, -24.73508]
      },
      "properties": { "name": "value398" }
    },
    {
      "type": "Feature",
      "geometry": {
        "type": "Point",
        "coordinates": [31.246890000000004, -25.05875]
      },
      "properties": { "name": "value399" }
    },
    {
      "type": "Feature",
      "geometry": {
        "type": "Point",
        "coordinates": [31.79607, -24.735229999999998]
      },
      "properties": { "name": "value400" }
    },
    {
      "type": "Feature",
      "geometry": {
        "type": "Point",
        "coordinates": [31.7954599999999, -24.735529999999997]
      },
      "properties": { "name": "value401" }
    },
    {
      "type": "Feature",
      "geometry": {
        "type": "Point",
        "coordinates": [31.79447, -24.7352099999999]
      },
      "properties": { "name": "value402" }
    },
    {
      "type": "Feature",
      "geometry": {
        "type": "Point",
        "coordinates": [31.7941399999999, -24.7348299999999]
      },
      "properties": { "name": "value403" }
    },
    {
      "type": "Feature",
      "geometry": { "type": "Point", "coordinates": [31.24682, -25.05882] },
      "properties": { "name": "value404" }
    },
    {
      "type": "Feature",
      "geometry": { "type": "Point", "coordinates": [31.7941, -24.73488] },
      "properties": { "name": "value405" }
    },
    {
      "type": "Feature",
      "geometry": {
        "type": "Point",
        "coordinates": [31.7941499999999, -24.7349999999999]
      },
      "properties": { "name": "value406" }
    },
    {
      "type": "Feature",
      "geometry": {
        "type": "Point",
        "coordinates": [31.7931199999999, -24.7340699999999]
      },
      "properties": { "name": "value407" }
    },
    {
      "type": "Feature",
      "geometry": { "type": "Point", "coordinates": [31.79322, -24.7342] },
      "properties": { "name": "value408" }
    },
    {
      "type": "Feature",
      "geometry": {
        "type": "Point",
        "coordinates": [31.2429799999999, -25.05927]
      },
      "properties": { "name": "value409" }
    },
    {
      "type": "Feature",
      "geometry": {
        "type": "Point",
        "coordinates": [31.7941, -24.7340899999999]
      },
      "properties": { "name": "value410" }
    },
    {
      "type": "Feature",
      "geometry": {
        "type": "Point",
        "coordinates": [31.242729999999998, -25.0588599999999]
      },
      "properties": { "name": "value411" }
    },
    {
      "type": "Feature",
      "geometry": {
        "type": "Point",
        "coordinates": [31.24097, -25.0583899999999]
      },
      "properties": { "name": "value412" }
    },
    {
      "type": "Feature",
      "geometry": {
        "type": "Point",
        "coordinates": [31.2403499999999, -25.0583899999999]
      },
      "properties": { "name": "value413" }
    },
    {
      "type": "Feature",
      "geometry": {
        "type": "Point",
        "coordinates": [31.7952699999999, -24.73263]
      },
      "properties": { "name": "value414" }
    },
    {
      "type": "Feature",
      "geometry": {
        "type": "Point",
        "coordinates": [31.2388499999999, -25.0580199999999]
      },
      "properties": { "name": "value415" }
    },
    {
      "type": "Feature",
      "geometry": {
        "type": "Point",
        "coordinates": [31.7948799999999, -24.73261]
      },
      "properties": { "name": "value416" }
    },
    {
      "type": "Feature",
      "geometry": {
        "type": "Point",
        "coordinates": [31.2374499999999, -25.0568199999999]
      },
      "properties": { "name": "value417" }
    },
    {
      "type": "Feature",
      "geometry": { "type": "Point", "coordinates": [31.79477, -24.73252] },
      "properties": { "name": "value418" }
    },
    {
      "type": "Feature",
      "geometry": { "type": "Point", "coordinates": [31.2372, -25.05433] },
      "properties": { "name": "value419" }
    },
    {
      "type": "Feature",
      "geometry": { "type": "Point", "coordinates": [31.79457, -24.73265] },
      "properties": { "name": "value420" }
    },
    {
      "type": "Feature",
      "geometry": { "type": "Point", "coordinates": [31.2371, -25.05228] },
      "properties": { "name": "value421" }
    },
    {
      "type": "Feature",
      "geometry": {
        "type": "Point",
        "coordinates": [31.7942199999999, -24.7328699999999]
      },
      "properties": { "name": "value422" }
    },
    {
      "type": "Feature",
      "geometry": {
        "type": "Point",
        "coordinates": [31.235529999999997, -25.050539999999998]
      },
      "properties": { "name": "value423" }
    },
    {
      "type": "Feature",
      "geometry": {
        "type": "Point",
        "coordinates": [31.234779999999997, -25.05037]
      },
      "properties": { "name": "value424" }
    },
    {
      "type": "Feature",
      "geometry": {
        "type": "Point",
        "coordinates": [31.2330599999999, -25.0516]
      },
      "properties": { "name": "value425" }
    },
    {
      "type": "Feature",
      "geometry": { "type": "Point", "coordinates": [31.79407, -24.73328] },
      "properties": { "name": "value426" }
    },
    {
      "type": "Feature",
      "geometry": {
        "type": "Point",
        "coordinates": [31.7941399999999, -24.7332]
      },
      "properties": { "name": "value427" }
    },
    {
      "type": "Feature",
      "geometry": {
        "type": "Point",
        "coordinates": [31.7941499999999, -24.73325]
      },
      "properties": { "name": "value428" }
    },
    {
      "type": "Feature",
      "geometry": {
        "type": "Point",
        "coordinates": [31.7946099999999, -24.73327]
      },
      "properties": { "name": "value429" }
    },
    {
      "type": "Feature",
      "geometry": { "type": "Point", "coordinates": [31.2257, -25.05348] },
      "properties": { "name": "value430" }
    },
    {
      "type": "Feature",
      "geometry": { "type": "Point", "coordinates": [31.22699, -25.05275] },
      "properties": { "name": "value431" }
    },
    {
      "type": "Feature",
      "geometry": { "type": "Point", "coordinates": [31.22765, -25.05256] },
      "properties": { "name": "value432" }
    },
    {
      "type": "Feature",
      "geometry": { "type": "Point", "coordinates": [31.2283, -25.05245] },
      "properties": { "name": "value433" }
    },
    {
      "type": "Feature",
      "geometry": {
        "type": "Point",
        "coordinates": [31.2285299999999, -25.05264]
      },
      "properties": { "name": "value434" }
    },
    {
      "type": "Feature",
      "geometry": { "type": "Point", "coordinates": [31.22819, -25.05345] },
      "properties": { "name": "value435" }
    },
    {
      "type": "Feature",
      "geometry": {
        "type": "Point",
        "coordinates": [31.229809999999997, -25.05946]
      },
      "properties": { "name": "value436" }
    },
    {
      "type": "Feature",
      "geometry": {
        "type": "Point",
        "coordinates": [31.2313499999999, -25.06294]
      },
      "properties": { "name": "value437" }
    },
    {
      "type": "Feature",
      "geometry": {
        "type": "Point",
        "coordinates": [31.2300499999999, -25.06557]
      },
      "properties": { "name": "value438" }
    },
    {
      "type": "Feature",
      "geometry": { "type": "Point", "coordinates": [31.23027, -25.06624] },
      "properties": { "name": "value439" }
    },
    {
      "type": "Feature",
      "geometry": {
        "type": "Point",
        "coordinates": [31.231890000000003, -25.06625]
      },
      "properties": { "name": "value440" }
    },
    {
      "type": "Feature",
      "geometry": {
        "type": "Point",
        "coordinates": [31.2317399999999, -25.067989999999998]
      },
      "properties": { "name": "value441" }
    },
    {
      "type": "Feature",
      "geometry": {
        "type": "Point",
        "coordinates": [31.2344599999999, -25.07035]
      },
      "properties": { "name": "value442" }
    },
    {
      "type": "Feature",
      "geometry": {
        "type": "Point",
        "coordinates": [31.2362399999999, -25.0714299999999]
      },
      "properties": { "name": "value443" }
    },
    {
      "type": "Feature",
      "geometry": {
        "type": "Point",
        "coordinates": [31.237479999999998, -25.0704899999999]
      },
      "properties": { "name": "value444" }
    },
    {
      "type": "Feature",
      "geometry": {
        "type": "Point",
        "coordinates": [31.238429999999997, -25.06943]
      },
      "properties": { "name": "value445" }
    },
    {
      "type": "Feature",
      "geometry": {
        "type": "Point",
        "coordinates": [31.2388, -25.0691899999999]
      },
      "properties": { "name": "value446" }
    },
    {
      "type": "Feature",
      "geometry": {
        "type": "Point",
        "coordinates": [31.23994, -25.0683599999999]
      },
      "properties": { "name": "value447" }
    },
    {
      "type": "Feature",
      "geometry": {
        "type": "Point",
        "coordinates": [31.2404699999999, -25.0681499999999]
      },
      "properties": { "name": "value448" }
    },
    {
      "type": "Feature",
      "geometry": {
        "type": "Point",
        "coordinates": [31.240609999999997, -25.067429999999998]
      },
      "properties": { "name": "value449" }
    },
    {
      "type": "Feature",
      "geometry": {
        "type": "Point",
        "coordinates": [31.2405499999999, -25.06736]
      },
      "properties": { "name": "value450" }
    },
    {
      "type": "Feature",
      "geometry": {
        "type": "Point",
        "coordinates": [31.2405599999999, -25.0673999999999]
      },
      "properties": { "name": "value451" }
    },
    {
      "type": "Feature",
      "geometry": {
        "type": "Point",
        "coordinates": [31.240509999999997, -25.06739]
      },
      "properties": { "name": "value452" }
    },
    {
      "type": "Feature",
      "geometry": {
        "type": "Point",
        "coordinates": [31.240509999999997, -25.0674999999999]
      },
      "properties": { "name": "value453" }
    },
    {
      "type": "Feature",
      "geometry": {
        "type": "Point",
        "coordinates": [31.2403499999999, -25.06748]
      },
      "properties": { "name": "value454" }
    },
    {
      "type": "Feature",
      "geometry": {
        "type": "Point",
        "coordinates": [31.2406599999999, -25.06736]
      },
      "properties": { "name": "value455" }
    },
    {
      "type": "Feature",
      "geometry": { "type": "Point", "coordinates": [31.24118, -25.06738] },
      "properties": { "name": "value456" }
    },
    {
      "type": "Feature",
      "geometry": {
        "type": "Point",
        "coordinates": [31.2413999999999, -25.06711]
      },
      "properties": { "name": "value457" }
    },
    {
      "type": "Feature",
      "geometry": {
        "type": "Point",
        "coordinates": [31.2411299999999, -25.066999999999997]
      },
      "properties": { "name": "value458" }
    },
    {
      "type": "Feature",
      "geometry": {
        "type": "Point",
        "coordinates": [31.2406299999999, -25.0665499999999]
      },
      "properties": { "name": "value459" }
    },
    {
      "type": "Feature",
      "geometry": {
        "type": "Point",
        "coordinates": [31.239390000000004, -25.0657099999999]
      },
      "properties": { "name": "value460" }
    },
    {
      "type": "Feature",
      "geometry": {
        "type": "Point",
        "coordinates": [31.23817, -25.0649699999999]
      },
      "properties": { "name": "value461" }
    },
    {
      "type": "Feature",
      "geometry": {
        "type": "Point",
        "coordinates": [31.2371699999999, -25.06417]
      },
      "properties": { "name": "value462" }
    },
    {
      "type": "Feature",
      "geometry": {
        "type": "Point",
        "coordinates": [31.2357799999999, -25.06363]
      },
      "properties": { "name": "value463" }
    },
    {
      "type": "Feature",
      "geometry": {
        "type": "Point",
        "coordinates": [31.235429999999997, -25.0630999999999]
      },
      "properties": { "name": "value464" }
    },
    {
      "type": "Feature",
      "geometry": {
        "type": "Point",
        "coordinates": [31.23457, -25.0623399999999]
      },
      "properties": { "name": "value465" }
    },
    {
      "type": "Feature",
      "geometry": {
        "type": "Point",
        "coordinates": [31.2341599999999, -25.0620599999999]
      },
      "properties": { "name": "value466" }
    },
    {
      "type": "Feature",
      "geometry": {
        "type": "Point",
        "coordinates": [31.2336999999999, -25.0618799999999]
      },
      "properties": { "name": "value467" }
    },
    {
      "type": "Feature",
      "geometry": {
        "type": "Point",
        "coordinates": [31.231109999999997, -25.0612199999999]
      },
      "properties": { "name": "value468" }
    },
    {
      "type": "Feature",
      "geometry": {
        "type": "Point",
        "coordinates": [31.229509999999998, -25.05946]
      },
      "properties": { "name": "value469" }
    },
    {
      "type": "Feature",
      "geometry": {
        "type": "Point",
        "coordinates": [31.228, -25.0568199999999]
      },
      "properties": { "name": "value470" }
    },
    {
      "type": "Feature",
      "geometry": {
        "type": "Point",
        "coordinates": [31.2281599999999, -25.05636]
      },
      "properties": { "name": "value471" }
    },
    {
      "type": "Feature",
      "geometry": {
        "type": "Point",
        "coordinates": [31.228109999999997, -25.05537]
      },
      "properties": { "name": "value472" }
    },
    {
      "type": "Feature",
      "geometry": { "type": "Point", "coordinates": [31.22802, -25.05451] },
      "properties": { "name": "value473" }
    },
    {
      "type": "Feature",
      "geometry": {
        "type": "Point",
        "coordinates": [31.2279599999999, -25.0540899999999]
      },
      "properties": { "name": "value474" }
    },
    {
      "type": "Feature",
      "geometry": {
        "type": "Point",
        "coordinates": [31.2295799999999, -25.0559699999999]
      },
      "properties": { "name": "value475" }
    },
    {
      "type": "Feature",
      "geometry": {
        "type": "Point",
        "coordinates": [31.2316399999999, -25.05779]
      },
      "properties": { "name": "value476" }
    },
    {
      "type": "Feature",
      "geometry": {
        "type": "Point",
        "coordinates": [31.2345299999999, -25.05997]
      },
      "properties": { "name": "value477" }
    },
    {
      "type": "Feature",
      "geometry": {
        "type": "Point",
        "coordinates": [31.234659999999998, -25.05995]
      },
      "properties": { "name": "value478" }
    },
    {
      "type": "Feature",
      "geometry": {
        "type": "Point",
        "coordinates": [31.23443, -25.0594299999999]
      },
      "properties": { "name": "value479" }
    },
    {
      "type": "Feature",
      "geometry": {
        "type": "Point",
        "coordinates": [31.2361, -25.0596199999999]
      },
      "properties": { "name": "value480" }
    },
    {
      "type": "Feature",
      "geometry": {
        "type": "Point",
        "coordinates": [31.240340000000003, -25.06213]
      },
      "properties": { "name": "value481" }
    },
    {
      "type": "Feature",
      "geometry": {
        "type": "Point",
        "coordinates": [31.243029999999997, -25.0642299999999]
      },
      "properties": { "name": "value482" }
    },
    {
      "type": "Feature",
      "geometry": {
        "type": "Point",
        "coordinates": [31.2434499999999, -25.06428]
      },
      "properties": { "name": "value483" }
    },
    {
      "type": "Feature",
      "geometry": {
        "type": "Point",
        "coordinates": [31.24367, -25.0649799999999]
      },
      "properties": { "name": "value484" }
    },
    {
      "type": "Feature",
      "geometry": {
        "type": "Point",
        "coordinates": [31.243509999999997, -25.06493]
      },
      "properties": { "name": "value485" }
    },
    {
      "type": "Feature",
      "geometry": { "type": "Point", "coordinates": [31.2439, -25.06631] },
      "properties": { "name": "value486" }
    },
    {
      "type": "Feature",
      "geometry": {
        "type": "Point",
        "coordinates": [31.2428999999999, -25.0657199999999]
      },
      "properties": { "name": "value487" }
    },
    {
      "type": "Feature",
      "geometry": {
        "type": "Point",
        "coordinates": [31.241529999999997, -25.06522]
      },
      "properties": { "name": "value488" }
    },
    {
      "type": "Feature",
      "geometry": {
        "type": "Point",
        "coordinates": [31.240029999999997, -25.06482]
      },
      "properties": { "name": "value489" }
    },
    {
      "type": "Feature",
      "geometry": {
        "type": "Point",
        "coordinates": [31.23992, -25.0646899999999]
      },
      "properties": { "name": "value490" }
    },
    {
      "type": "Feature",
      "geometry": {
        "type": "Point",
        "coordinates": [31.2395199999999, -25.0646099999999]
      },
      "properties": { "name": "value491" }
    },
    {
      "type": "Feature",
      "geometry": {
        "type": "Point",
        "coordinates": [31.238459999999996, -25.0636399999999]
      },
      "properties": { "name": "value492" }
    },
    {
      "type": "Feature",
      "geometry": {
        "type": "Point",
        "coordinates": [31.240409999999997, -25.0641299999999]
      },
      "properties": { "name": "value493" }
    },
    {
      "type": "Feature",
      "geometry": { "type": "Point", "coordinates": [31.2425, -25.06483] },
      "properties": { "name": "value494" }
    },
    {
      "type": "Feature",
      "geometry": {
        "type": "Point",
        "coordinates": [31.24254, -25.064729999999997]
      },
      "properties": { "name": "value495" }
    },
    {
      "type": "Feature",
      "geometry": { "type": "Point", "coordinates": [31.24258, -25.06481] },
      "properties": { "name": "value496" }
    },
    {
      "type": "Feature",
      "geometry": {
        "type": "Point",
        "coordinates": [31.2425999999999, -25.06482]
      },
      "properties": { "name": "value497" }
    },
    {
      "type": "Feature",
      "geometry": {
        "type": "Point",
        "coordinates": [31.24258, -25.0653299999999]
      },
      "properties": { "name": "value498" }
    }
  ]
}
